setup.cfg
setup.py
es_wrapper/__init__.py
es_wrapper.egg-info/PKG-INFO
es_wrapper.egg-info/SOURCES.txt
es_wrapper.egg-info/dependency_links.txt
es_wrapper.egg-info/requires.txt
es_wrapper.egg-info/top_level.txt
es_wrapper/configuration/__init__.py
es_wrapper/configuration/mappings.py
es_wrapper/configuration/parameters.py
es_wrapper/configuration/queries.py
es_wrapper/configuration/setup.py
es_wrapper/general/__init__.py
es_wrapper/general/datatypes.py
es_wrapper/general/formats.py
es_wrapper/general/http_funcs.py
es_wrapper/general/log.py
es_wrapper/general/strings.py
es_wrapper/tools/__init__.py
es_wrapper/tools/copy_dashboard.py
es_wrapper/tools/es_adapter.py
es_wrapper/tools/infra.py
es_wrapper/tools/reindex.py