Metadata-Version: 1.1
Name: es-wrapper
Version: 1.0.21
Summary: A wrapper package for easy Elasticsearch Interface
Home-page: https://github.com/guyeshet/es_wrapper_package.git
Author: Guy Eshet
Author-email: guyeshet@gmail.com
License: Apache 2.0
Keywords: elasticsearch
Platform: UNKNOWN
Classifier: Development Status :: 5 - Production/Stable
Classifier: Intended Audience :: Developers
Classifier: License :: OSI Approved :: Apache Software License
Classifier: Operating System :: POSIX
Classifier: Topic :: Internet :: WWW/HTTP
